open_sesame/LFP SoC-OCV.csv
open_sesame/LTO SoC-OCV.csv
open_sesame/NMC SOC-OCV 2.csv
open_sesame/VERSION
open_sesame/__init__.py
open_sesame/cell.py
open_sesame/chemicallibrary.py
open_sesame/chemicallibrary_LFP.py
open_sesame/chemicallibrary_LTO.py
open_sesame/chemicallibrary_NMC.py
open_sesame/cyc_counting_algorithm.py
open_sesame/degradation_analysis.py
open_sesame/perf_analysis.py
"open_sesame/r-soc-temp (extensive,1Hz).csv"
open_sesame/sim_engine.py
open_sesame/sim_engine_function.py
open_sesame/sim_engine_function_SoC.py
open_sesame/simulation_input.py
open_sesame/simulation_input_SoC.py
open_sesame/simulation_output.py
open_sesame/simulation_parameter.py
open_sesame/testfile_cycles.csv
open_sesame/thermal_model.py
Open_SESAME_Battery-1.2.0.dist-info/LICENSE.txt
Open_SESAME_Battery-1.2.0.dist-info/METADATA
Open_SESAME_Battery-1.2.0.dist-info/WHEEL
Open_SESAME_Battery-1.2.0.dist-info/top_level.txt
Open_SESAME_Battery-1.2.0.dist-info/RECORD
