Metadata-Version: 2.1
Name: Open-SESAME-Battery
Version: 1.2.0
Summary: Open source battery lifetime simulation software
Home-page: https://gitlab.ti.bfh.ch/oss/esrec/open-sesame
Author: "Marco Beyeler, Shubham Sharad, Stefan Broennimann, Yoann Moullet"
Author-email: energy@bfh.ch
License: MIT
Project-URL: Source, https://gitlab.ti.bfh.ch/oss/esrec/open-sesame
Platform: any
Classifier: Development Status :: 4 - Beta
Classifier: Programming Language :: Python
Requires-Python: >=3.8
License-File: LICENSE.txt
Requires-Dist: matplotlib
Requires-Dist: numpy
Requires-Dist: pandas
Requires-Dist: rainflow
Requires-Dist: scipy
Requires-Dist: seaborn
Provides-Extra: testing
Requires-Dist: setuptools ; extra == 'testing'
Requires-Dist: pytest ; extra == 'testing'
Requires-Dist: pytest-cov ; extra == 'testing'
